{
  "language" : "agq",
  "territories" : {
    "af" : "Afɨlekà ghɨ Emàm ghò",
    "af-NA" : "Nàmibìa",
    "agq" : "Kàmàlûŋ",
    "ak" : "Gaanà",
    "am" : "Ètyǒpìa",
    "ar-AE" : "Yùnaetɛ Alab ɛmelɛ̀",
    "ar-BH" : "Bàlaen",
    "ar-DJ" : "Dzìbuwtì",
    "ar-DZ" : "Àadzɛlìa",
    "ar-EG" : "Edzì",
    "ar-EH" : "EH",
    "ar-ER" : "Èletɨ̀là",
    "ar-IL" : "Ezɨ̀lɛ̂",
    "ar-IQ" : "Èlâkɨ̀",
    "ar-JO" : "Dzodàn",
    "ar-KM" : "Komolòs",
    "ar-KW" : "Kùwɛ̂",
    "ar-LB" : "Lɛbanè",
    "ar-LY" : "Lebìa",
    "ar-MA" : "Mòlokò",
    "ar-MR" : "Mùlètanyìa",
    "ar-OM" : "Umàn",
    "ar-PS" : "Adzɨmā kɨ ŋgùŋ kɨ Palɛsɨtɨnyia à kɨ Gazà kò",
    "ar-QA" : "Katà",
    "ar-SA" : "Sawudi Alabi",
    "ar-SD" : "Sùdân",
    "ar-SO" : "Sòmalìa",
    "ar-SS" : "SS",
    "ar-SY" : "Silîa",
    "ar-TD" : "Châ",
    "ar-TN" : "Tùneshìa",
    "ar-YE" : "Yɛmɛ̀n",
    "as" : "Endìa",
    "asa" : "Tàanzanyìa",
    "ast" : "Sɨ̀kpɛ̂n",
    "az-Cyrl" : "Àzɨbɛ̀dzân",
    "az-Latn" : "Àzɨbɛ̀dzân",
    "bas" : "Kàmàlûŋ",
    "be" : "Bɛlàlûs",
    "bem" : "Zambìa",
    "bez" : "Tàanzanyìa",
    "bg" : "Bùugɛlìa",
    "bm" : "Malè",
    "bn" : "Baŋgɨ̀làdɛ̂",
    "bn-IN" : "Endìa",
    "bo" : "Chaenà",
    "bo-IN" : "Endìa",
    "br" : "Fàlâŋnsì",
    "brx" : "Endìa",
    "bs-Cyrl" : "Bosɨnyìa à Hɛ̀zɛ̀gòvinà",
    "bs-Latn" : "Bosɨnyìa à Hɛ̀zɛ̀gòvinà",
    "ca" : "Sɨ̀kpɛ̂n",
    "ca-AD" : "Àndolà",
    "ca-ES-VALENCIA" : "Sɨ̀kpɛ̂n",
    "ca-FR" : "Fàlâŋnsì",
    "ca-IT" : "Etalè",
    "ccp" : "Baŋgɨ̀làdɛ̂",
    "ccp-IN" : "Endìa",
    "ce" : "Loshìa",
    "cgg" : "Yùgandà",
    "chr" : "USA",
    "ckb" : "Èlâkɨ̀",
    "ckb-IR" : "Èlân",
    "cs" : "Chɛ̂ Lèkpubèlè",
    "cu" : "Loshìa",
    "cy" : "Yùnaetɛ Kiŋdɔ̀m",
    "da" : "Dɛnɨmà",
    "da-GL" : "Gɨ̀lenlân",
    "dav" : "Kɨnyà",
    "de" : "Dzamanè",
    "de-AT" : "Usɨtɨ̀là",
    "de-BE" : "Bɛɛdzwùm",
    "de-CH" : "Suezàlân",
    "de-IT" : "Etalè",
    "de-LI" : "Letɨnshɨ̀n",
    "de-LU" : "Luzɨmbùʔ",
    "dje" : "Naedzà",
    "dsb" : "Dzamanè",
    "dua" : "Kàmàlûŋ",
    "dyo" : "Sɛ̀nɛ̀gâa",
    "dz" : "Mbutàn",
    "ebu" : "Kɨnyà",
    "ee" : "Gaanà",
    "ee-TG" : "Tugù",
    "el" : "Gɨ̀lês",
    "el-CY" : "Saekpùlù",
    "en" : "USA",
    "en-AG" : "Àntigwà à Bàbudà",
    "en-AI" : "Àŋgwilà",
    "en-AS" : "Àmɛlekan Samwà",
    "en-AT" : "Usɨtɨ̀là",
    "en-AU" : "Ùsɨ̀tɛ̀lɛlìa",
    "en-BB" : "Bàbadòs",
    "en-BE" : "Bɛɛdzwùm",
    "en-BI" : "Bùlundì",
    "en-BM" : "Bɛ̀mudà",
    "en-BS" : "Bàhamàs",
    "en-BW" : "Bòtɨ̀swǎnà",
    "en-BZ" : "Bɛ̀lezɨ̀",
    "en-CA" : "Kanadà",
    "en-CC" : "CC",
    "en-CH" : "Suezàlân",
    "en-CK" : "Chwɨla ŋ̀ Kûʔ",
    "en-CM" : "Kàmàlûŋ",
    "en-CX" : "CX",
    "en-CY" : "Saekpùlù",
    "en-DE" : "Dzamanè",
    "en-DG" : "DG",
    "en-DK" : "Dɛnɨmà",
    "en-DM" : "Dòmenekà",
    "en-ER" : "Èletɨ̀là",
    "en-FI" : "Fɨnlàn",
    "en-FJ" : "Fidzi",
    "en-FK" : "Chwɨlà fɨ Fakɨlàn",
    "en-FM" : "Maekòlòneshìa",
    "en-GB" : "Yùnaetɛ Kiŋdɔ̀m",
    "en-GD" : "Gɨ̀lɛnadà",
    "en-GG" : "GG",
    "en-GH" : "Gaanà",
    "en-GI" : "Dzibɨ̀latà",
    "en-GM" : "Gambìa",
    "en-GU" : "Gwam",
    "en-GY" : "Gùyanà",
    "en-HK" : "HK",
    "en-IE" : "Aelɨ̀lân",
    "en-IL" : "Ezɨ̀lɛ̂",
    "en-IM" : "IM",
    "en-IN" : "Endìa",
    "en-IO" : "Dɨŋò kɨ dzughùnstòʔ kɨ Endìa kɨ Bɨ̀letì kò",
    "en-JE" : "JE",
    "en-JM" : "Dzàmɛkà",
    "en-KE" : "Kɨnyà",
    "en-KI" : "Kèlèbati",
    "en-KN" : "Sɛ̀n Kî à Nevì",
    "en-KY" : "Chwɨlà ŋ̀ Kaemàn",
    "en-LC" : "Sɛ̀n Lushìa",
    "en-LR" : "Làebɛlìa",
    "en-LS" : "Lɛ̀sotù",
    "en-MG" : "Màdàgasɨkà",
    "en-MH" : "Chwɨlà fɨ Mashà",
    "en-MO" : "MO",
    "en-MP" : "Chwɨlà m̀ Màlǐanà mɨ̀ Ekùw mò",
    "en-MS" : "Mùŋtselà",
    "en-MT" : "Maatà",
    "en-MU" : "Mùleshwɨ̀s",
    "en-MW" : "Màlawì",
    "en-MY" : "Màlɛshìa",
    "en-NA" : "Nàmibìa",
    "en-NF" : "Chwɨlà fɨ Nufòʔ",
    "en-NG" : "Gɨ̀anyɨ",
    "en-NL" : "Nedàlân",
    "en-NR" : "Nàwulù",
    "en-NU" : "Niyu",
    "en-NZ" : "Zìlân È fūghū",
    "en-PG" : "Kpakpua Ginè È fūghū",
    "en-PH" : "Felèkpî",
    "en-PK" : "Kpakìsɨ̀tân",
    "en-PN" : "Kpitɨ̀kalè",
    "en-PR" : "Kpǒto Leko",
    "en-PW" : "Kpàlawù",
    "en-RW" : "Lùwandà",
    "en-SB" : "Chwɨlà fɨ Solomwɨ̀n",
    "en-SC" : "Sɛchɛ̀lɛ̀s",
    "en-SD" : "Sùdân",
    "en-SE" : "Suedɨ̀n",
    "en-SG" : "Siŋgàkpôo",
    "en-SH" : "Sɛ̀n Èlenà",
    "en-SI" : "Sɨ̀lòvɨnyìa",
    "en-SL" : "Silìa lûŋ",
    "en-SS" : "SS",
    "en-SX" : "SX",
    "en-SZ" : "Shǔazìlân",
    "en-TC" : "Chwɨla n Tɨtê à Kaekùs",
    "en-TK" : "Tuwkelawù",
    "en-TO" : "Tuŋgà",
    "en-TT" : "Tèlenedà à Tòbagù",
    "en-TV" : "Tuwvalùw",
    "en-TZ" : "Tàanzanyìa",
    "en-UG" : "Yùgandà",
    "en-UM" : "UM",
    "en-US-POSIX" : "USA",
    "en-VC" : "Sɛ̀n Vinsɨ̀n à Gɨlenadi Ù tē",
    "en-VG" : "Chwɨlà m̀ Vidzinyìa m̀ Bɨ̀letì mò",
    "en-VI" : "U. S. Chwɨlà fɨ Mbuʔmbu",
    "en-VU" : "Vànǔatùw",
    "en-WS" : "Sàmowà",
    "en-ZA" : "Afɨlekà ghɨ Emàm ghò",
    "en-ZM" : "Zambìa",
    "en-ZW" : "Zìmbagbɛ̀",
    "es" : "Sɨ̀kpɛ̂n",
    "es-AR" : "Àdzɛ̀ntinà",
    "es-BO" : "Bòlevà",
    "es-BR" : "Bɨ̀làzîi",
    "es-BZ" : "Bɛ̀lezɨ̀",
    "es-CL" : "Chilè",
    "es-CO" : "Kòlombìa",
    "es-CR" : "Kòsɨ̀tà Lekà",
    "es-CU" : "Kuuwbà",
    "es-DO" : "Dòmenekà Lèkpubèlè",
    "es-EA" : "EA",
    "es-EC" : "Ekwadò",
    "es-GQ" : "Èkwɛ̀tolia Ginè",
    "es-GT" : "Gwàtɨ̀malà",
    "es-HN" : "Hɔndulàs",
    "es-IC" : "IC",
    "es-MX" : "Mɛkɨzikù",
    "es-NI" : "Nikàlagwà",
    "es-PA" : "Kpanàma",
    "es-PE" : "Kpɛlû",
    "es-PH" : "Felèkpî",
    "es-PR" : "Kpǒto Leko",
    "es-PY" : "Kpalàgwɛ̂",
    "es-SV" : "Esàvadò",
    "es-US" : "USA",
    "es-UY" : "Yulùgwɛ̂",
    "es-VE" : "Vɛ̀nɛ̀zǔɛɛlà",
    "et" : "Èsɨ̀tonyìa",
    "eu" : "Sɨ̀kpɛ̂n",
    "ewo" : "Kàmàlûŋ",
    "fa" : "Èlân",
    "fa-AF" : "Àfɨ̀ganìsɨ̀tân",
    "ff" : "Sɛ̀nɛ̀gâa",
    "ff-CM" : "Kàmàlûŋ",
    "ff-GN" : "Ginè",
    "ff-MR" : "Mùlètanyìa",
    "fi" : "Fɨnlàn",
    "fil" : "Felèkpî",
    "fo" : "FO",
    "fo-DK" : "Dɛnɨmà",
    "fr" : "Fàlâŋnsì",
    "fr-BE" : "Bɛɛdzwùm",
    "fr-BF" : "Bùkinà Fasò",
    "fr-BI" : "Bùlundì",
    "fr-BJ" : "Bɛ̀nɨ̂ŋ",
    "fr-BL" : "BL",
    "fr-CA" : "Kanadà",
    "fr-CD" : "Dɛ̀mùkàlatì Lèkpubèlè è Kuŋgù",
    "fr-CF" : "Sɛnta Afɨlekan Lèkpobèlè",
    "fr-CG" : "Kuŋgù",
    "fr-CH" : "Suezàlân",
    "fr-CI" : "Ku Dɨ̀vûa",
    "fr-CM" : "Kàmàlûŋ",
    "fr-DJ" : "Dzìbuwtì",
    "fr-DZ" : "Àadzɛlìa",
    "fr-GA" : "Gàbûn",
    "fr-GF" : "Gàyanà è Fàlâŋnsì",
    "fr-GN" : "Ginè",
    "fr-GP" : "Gwadalukpɛ̀",
    "fr-GQ" : "Èkwɛ̀tolia Ginè",
    "fr-HT" : "Hǎetì",
    "fr-KM" : "Komolòs",
    "fr-LU" : "Luzɨmbùʔ",
    "fr-MA" : "Mòlokò",
    "fr-MC" : "Mùnaku",
    "fr-MF" : "MF",
    "fr-MG" : "Màdàgasɨkà",
    "fr-ML" : "Malè",
    "fr-MQ" : "Màtìnekì",
    "fr-MR" : "Mùlètanyìa",
    "fr-MU" : "Mùleshwɨ̀s",
    "fr-NC" : "Kàlèdonyìa È fūghū",
    "fr-NE" : "Naedzà",
    "fr-PF" : "Kpoleneshìa è Fàlâŋnsì",
    "fr-PM" : "Sɛ̀n Kpiyɛ̀ à Mikelɔŋ",
    "fr-RE" : "Lèyunyɔ̀ŋ",
    "fr-RW" : "Lùwandà",
    "fr-SC" : "Sɛchɛ̀lɛ̀s",
    "fr-SN" : "Sɛ̀nɛ̀gâa",
    "fr-SY" : "Silîa",
    "fr-TD" : "Châ",
    "fr-TG" : "Tugù",
    "fr-TN" : "Tùneshìa",
    "fr-VU" : "Vànǔatùw",
    "fr-WF" : "Wales à Fùwtuwnà",
    "fr-YT" : "Màyotì",
    "fur" : "Etalè",
    "fy" : "Nedàlân",
    "ga" : "Aelɨ̀lân",
    "gd" : "Yùnaetɛ Kiŋdɔ̀m",
    "gl" : "Sɨ̀kpɛ̂n",
    "gsw" : "Suezàlân",
    "gsw-FR" : "Fàlâŋnsì",
    "gsw-LI" : "Letɨnshɨ̀n",
    "gu" : "Endìa",
    "guz" : "Kɨnyà",
    "gv" : "IM",
    "ha" : "Gɨ̀anyɨ",
    "ha-GH" : "Gaanà",
    "ha-NE" : "Naedzà",
    "haw" : "USA",
    "he" : "Ezɨ̀lɛ̂",
    "hi" : "Endìa",
    "hr" : "Kòwɛshìa",
    "hr-BA" : "Bosɨnyìa à Hɛ̀zɛ̀gòvinà",
    "hsb" : "Dzamanè",
    "hu" : "Hɔŋgàlè",
    "hy" : "Àmɛnyìa",
    "id" : "Èndòneshìa",
    "ig" : "Gɨ̀anyɨ",
    "ii" : "Chaenà",
    "is" : "Aesɨ̀lân",
    "it" : "Etalè",
    "it-CH" : "Suezàlân",
    "it-SM" : "Sàn Màlenù",
    "it-VA" : "Vatikàn Sɨ̀tɛ̂",
    "ja" : "Dzàkpân",
    "jgo" : "Kàmàlûŋ",
    "jmc" : "Tàanzanyìa",
    "ka" : "Dzɔɔdzìa",
    "kab" : "Àadzɛlìa",
    "kam" : "Kɨnyà",
    "kde" : "Tàanzanyìa",
    "kea" : "Chwɨla ŋ̀ Kɛ̀b Vɛ̂ɛ",
    "khq" : "Malè",
    "ki" : "Kɨnyà",
    "kk" : "Kàzasɨ̀tân",
    "kkj" : "Kàmàlûŋ",
    "kl" : "Gɨ̀lenlân",
    "kln" : "Kɨnyà",
    "km" : "Kàmbodìa",
    "kn" : "Endìa",
    "ko" : "Kùulîa, Emàm",
    "ko-KP" : "Kùulîa, Ekùw",
    "kok" : "Endìa",
    "ks" : "Endìa",
    "ksb" : "Tàanzanyìa",
    "ksf" : "Kàmàlûŋ",
    "ksh" : "Dzamanè",
    "kw" : "Yùnaetɛ Kiŋdɔ̀m",
    "ky" : "Kìdzisɨ̀tân",
    "lag" : "Tàanzanyìa",
    "lb" : "Luzɨmbùʔ",
    "lg" : "Yùgandà",
    "lkt" : "USA",
    "ln" : "Dɛ̀mùkàlatì Lèkpubèlè è Kuŋgù",
    "ln-AO" : "Àŋgolà",
    "ln-CF" : "Sɛnta Afɨlekan Lèkpobèlè",
    "ln-CG" : "Kuŋgù",
    "lo" : "Làwos",
    "lrc" : "Èlân",
    "lrc-IQ" : "Èlâkɨ̀",
    "lt" : "Lètwǎnyìa",
    "lu" : "Dɛ̀mùkàlatì Lèkpubèlè è Kuŋgù",
    "luo" : "Kɨnyà",
    "luy" : "Kɨnyà",
    "lv" : "Làtɨva",
    "mas" : "Kɨnyà",
    "mas-TZ" : "Tàanzanyìa",
    "mer" : "Kɨnyà",
    "mfe" : "Mùleshwɨ̀s",
    "mg" : "Màdàgasɨkà",
    "mgh" : "Mùzàmbî",
    "mgo" : "Kàmàlûŋ",
    "mk" : "Mɨ̀sɨ̀donyìa",
    "ml" : "Endìa",
    "mn" : "Mùŋgolìa",
    "mr" : "Endìa",
    "ms" : "Màlɛshìa",
    "ms-BN" : "Bɨ̀lunè",
    "ms-SG" : "Siŋgàkpôo",
    "mt" : "Maatà",
    "mua" : "Kàmàlûŋ",
    "my" : "Mǐanmà",
    "mzn" : "Èlân",
    "naq" : "Nàmibìa",
    "nb" : "Noowɛ̂ɛ",
    "nb-SJ" : "SJ",
    "nd" : "Zìmbagbɛ̀",
    "nds" : "Dzamanè",
    "nds-NL" : "Nedàlân",
    "ne" : "Nɛkpâa",
    "ne-IN" : "Endìa",
    "nl" : "Nedàlân",
    "nl-AW" : "Àlubà",
    "nl-BE" : "Bɛɛdzwùm",
    "nl-BQ" : "BQ",
    "nl-CW" : "CW",
    "nl-SR" : "Sulènamè",
    "nl-SX" : "SX",
    "nmg" : "Kàmàlûŋ",
    "nn" : "Noowɛ̂ɛ",
    "nnh" : "Kàmàlûŋ",
    "nus" : "SS",
    "nyn" : "Yùgandà",
    "om" : "Ètyǒpìa",
    "om-KE" : "Kɨnyà",
    "or" : "Endìa",
    "os" : "Dzɔɔdzìa",
    "os-RU" : "Loshìa",
    "pa-Arab" : "Kpakìsɨ̀tân",
    "pa-Guru" : "Endìa",
    "pl" : "Kpulàn",
    "ps" : "Àfɨ̀ganìsɨ̀tân",
    "pt" : "Bɨ̀làzîi",
    "pt-AO" : "Àŋgolà",
    "pt-CH" : "Suezàlân",
    "pt-CV" : "Chwɨla ŋ̀ Kɛ̀b Vɛ̂ɛ",
    "pt-GQ" : "Èkwɛ̀tolia Ginè",
    "pt-GW" : "Ginè Bìsawù",
    "pt-LU" : "Luzɨmbùʔ",
    "pt-MO" : "MO",
    "pt-MZ" : "Mùzàmbî",
    "pt-PT" : "Kputuwgà",
    "pt-ST" : "Sawo Tɔ̀me à Kpèlènsikpɛ̀",
    "pt-TL" : "Ês Taemò",
    "qu" : "Kpɛlû",
    "qu-BO" : "Bòlevà",
    "qu-EC" : "Ekwadò",
    "rm" : "Suezàlân",
    "rn" : "Bùlundì",
    "ro" : "Lùmanyìa",
    "ro-MD" : "Mòodovà",
    "rof" : "Tàanzanyìa",
    "ru" : "Loshìa",
    "ru-BY" : "Bɛlàlûs",
    "ru-KG" : "Kìdzisɨ̀tân",
    "ru-KZ" : "Kàzasɨ̀tân",
    "ru-MD" : "Mòodovà",
    "ru-UA" : "Yùkɛ̀lɛ̂",
    "rw" : "Lùwandà",
    "rwk" : "Tàanzanyìa",
    "sah" : "Loshìa",
    "saq" : "Kɨnyà",
    "sbp" : "Tàanzanyìa",
    "sd" : "Kpakìsɨ̀tân",
    "se" : "Noowɛ̂ɛ",
    "se-FI" : "Fɨnlàn",
    "se-SE" : "Suedɨ̀n",
    "seh" : "Mùzàmbî",
    "ses" : "Malè",
    "sg" : "Sɛnta Afɨlekan Lèkpobèlè",
    "shi-Latn" : "Mòlokò",
    "shi-Tfng" : "Mòlokò",
    "si" : "Sɨ̀le Laŋkà",
    "sk" : "Sɨ̀lòvɨkɨ̀a",
    "sl" : "Sɨ̀lòvɨnyìa",
    "smn" : "Fɨnlàn",
    "sn" : "Zìmbagbɛ̀",
    "so" : "Sòmalìa",
    "so-DJ" : "Dzìbuwtì",
    "so-ET" : "Ètyǒpìa",
    "so-KE" : "Kɨnyà",
    "sq" : "Àabɛnìa",
    "sq-MK" : "Mɨ̀sɨ̀donyìa",
    "sq-XK" : "XK",
    "sr-Cyrl" : "RS",
    "sr-Cyrl-BA" : "Bosɨnyìa à Hɛ̀zɛ̀gòvinà",
    "sr-Cyrl-ME" : "ME",
    "sr-Cyrl-XK" : "XK",
    "sr-Latn" : "RS",
    "sr-Latn-BA" : "Bosɨnyìa à Hɛ̀zɛ̀gòvinà",
    "sr-Latn-ME" : "ME",
    "sr-Latn-XK" : "XK",
    "sv" : "Suedɨ̀n",
    "sv-AX" : "AX",
    "sv-FI" : "Fɨnlàn",
    "sw" : "Tàanzanyìa",
    "sw-CD" : "Dɛ̀mùkàlatì Lèkpubèlè è Kuŋgù",
    "sw-KE" : "Kɨnyà",
    "sw-UG" : "Yùgandà",
    "ta" : "Endìa",
    "ta-LK" : "Sɨ̀le Laŋkà",
    "ta-MY" : "Màlɛshìa",
    "ta-SG" : "Siŋgàkpôo",
    "te" : "Endìa",
    "teo" : "Yùgandà",
    "teo-KE" : "Kɨnyà",
    "tg" : "Tàdzikìsɨ̀tân",
    "th" : "Taelàn",
    "ti" : "Ètyǒpìa",
    "ti-ER" : "Èletɨ̀là",
    "tk" : "Tekɨmènèsɨ̀tân",
    "to" : "Tuŋgà",
    "tr" : "Teekì",
    "tr-CY" : "Saekpùlù",
    "tt" : "Loshìa",
    "twq" : "Naedzà",
    "tzm" : "Mòlokò",
    "ug" : "Chaenà",
    "uk" : "Yùkɛ̀lɛ̂",
    "ur" : "Kpakìsɨ̀tân",
    "ur-IN" : "Endìa",
    "uz-Arab" : "Àfɨ̀ganìsɨ̀tân",
    "uz-Cyrl" : "Yùzɨ̀bɛkìsɨ̀tân",
    "uz-Latn" : "Yùzɨ̀bɛkìsɨ̀tân",
    "vai-Latn" : "Làebɛlìa",
    "vai-Vaii" : "Làebɛlìa",
    "vi" : "Vìyɛnàm",
    "vun" : "Tàanzanyìa",
    "wae" : "Suezàlân",
    "wo" : "Sɛ̀nɛ̀gâa",
    "xog" : "Yùgandà",
    "yav" : "Kàmàlûŋ",
    "yo" : "Gɨ̀anyɨ",
    "yo-BJ" : "Bɛ̀nɨ̂ŋ",
    "yue-Hans" : "Chaenà",
    "yue-Hant" : "HK",
    "zgh" : "Mòlokò",
    "zh-Hans" : "Chaenà",
    "zh-Hans-HK" : "HK",
    "zh-Hans-MO" : "MO",
    "zh-Hans-SG" : "Siŋgàkpôo",
    "zh-Hant" : "Taewàn",
    "zh-Hant-HK" : "HK",
    "zh-Hant-MO" : "MO",
    "zu" : "Afɨlekà ghɨ Emàm ghò"
  }
}