{
  "localeID" : "uk",
  "dateFields" : {
    "year" : {
      "displayName" : "рік",
      "relative-type-0" : "цього року",
      "relative-type-1" : "наступного року",
      "relative-type--1" : "торік",
      "relativeTime-type-future" : {
        "relativeTimePattern-count-other" : "через {0} року",
        "relativeTimePattern-count-many" : "через {0} років",
        "relativeTimePattern-count-one" : "через {0} рік",
        "relativeTimePattern-count-few" : "через {0} роки"
      },
      "relativeTime-type-past" : {
        "relativeTimePattern-count-other" : "{0} року тому",
        "relativeTimePattern-count-many" : "{0} років тому",
        "relativeTimePattern-count-one" : "{0} рік тому",
        "relativeTimePattern-count-few" : "{0} роки тому"
      }
    },
    "month" : {
      "displayName" : "місяць",
      "relative-type-0" : "цього місяця",
      "relative-type-1" : "наступного місяця",
      "relative-type--1" : "минулого місяця",
      "relativeTime-type-future" : {
        "relativeTimePattern-count-other" : "через {0} місяця",
        "relativeTimePattern-count-many" : "через {0} місяців",
        "relativeTimePattern-count-one" : "через {0} місяць",
        "relativeTimePattern-count-few" : "через {0} місяці"
      },
      "relativeTime-type-past" : {
        "relativeTimePattern-count-other" : "{0} місяця тому",
        "relativeTimePattern-count-many" : "{0} місяців тому",
        "relativeTimePattern-count-one" : "{0} місяць тому",
        "relativeTimePattern-count-few" : "{0} місяці тому"
      }
    },
    "day" : {
      "displayName" : "день",
      "relative-type-2" : "післязавтра",
      "relative-type-0" : "сьогодні",
      "relative-type-1" : "завтра",
      "relative-type--2" : "позавчора",
      "relative-type--1" : "учора",
      "relativeTime-type-future" : {
        "relativeTimePattern-count-other" : "через {0} дня",
        "relativeTimePattern-count-many" : "через {0} днів",
        "relativeTimePattern-count-one" : "через {0} день",
        "relativeTimePattern-count-few" : "через {0} дні"
      },
      "relativeTime-type-past" : {
        "relativeTimePattern-count-other" : "{0} дня тому",
        "relativeTimePattern-count-many" : "{0} днів тому",
        "relativeTimePattern-count-one" : "{0} день тому",
        "relativeTimePattern-count-few" : "{0} дні тому"
      }
    },
    "hour" : {
      "displayName" : "година",
      "relative-type-0" : "цієї години",
      "relativeTime-type-future" : {
        "relativeTimePattern-count-other" : "через {0} години",
        "relativeTimePattern-count-many" : "через {0} годин",
        "relativeTimePattern-count-one" : "через {0} годину",
        "relativeTimePattern-count-few" : "через {0} години"
      },
      "relativeTime-type-past" : {
        "relativeTimePattern-count-other" : "{0} години тому",
        "relativeTimePattern-count-many" : "{0} годин тому",
        "relativeTimePattern-count-one" : "{0} годину тому",
        "relativeTimePattern-count-few" : "{0} години тому"
      }
    },
    "minute" : {
      "displayName" : "хвилина",
      "relative-type-0" : "цієї хвилини",
      "relativeTime-type-future" : {
        "relativeTimePattern-count-other" : "через {0} хвилини",
        "relativeTimePattern-count-many" : "через {0} хвилин",
        "relativeTimePattern-count-one" : "через {0} хвилину",
        "relativeTimePattern-count-few" : "через {0} хвилини"
      },
      "relativeTime-type-past" : {
        "relativeTimePattern-count-other" : "{0} хвилини тому",
        "relativeTimePattern-count-many" : "{0} хвилин тому",
        "relativeTimePattern-count-one" : "{0} хвилину тому",
        "relativeTimePattern-count-few" : "{0} хвилини тому"
      }
    },
    "second" : {
      "displayName" : "секунда",
      "relative-type-0" : "зараз",
      "relativeTime-type-future" : {
        "relativeTimePattern-count-other" : "через {0} секунди",
        "relativeTimePattern-count-many" : "через {0} секунд",
        "relativeTimePattern-count-one" : "через {0} секунду",
        "relativeTimePattern-count-few" : "через {0} секунди"
      },
      "relativeTime-type-past" : {
        "relativeTimePattern-count-other" : "{0} секунди тому",
        "relativeTimePattern-count-many" : "{0} секунд тому",
        "relativeTimePattern-count-one" : "{0} секунду тому",
        "relativeTimePattern-count-few" : "{0} секунди тому"
      }
    }
  }
}