{
  "localeID" : "chr",
  "dateFields" : {
    "year" : {
      "displayName" : "ᎤᏕᏘᏴᏌᏗᏒᎢ",
      "relative-type-0" : "ᎯᎠ ᏧᏕᏘᏴᏒᏘ",
      "relative-type-1" : "ᎡᏘᏴᎢ",
      "relative-type--1" : "ᎡᏘ ᏥᎨᏒ",
      "relativeTime-type-future" : {
        "relativeTimePattern-count-other" : "ᎾᎿ {0} ᎢᏧᏕᏘᏴᏌᏗᏒᎢ",
        "relativeTimePattern-count-one" : "ᎾᎿ {0} ᎤᏕᏘᏴᏌᏗᏒᎢ"
      },
      "relativeTime-type-past" : {
        "relativeTimePattern-count-other" : "{0} ᎢᏧᏕᏘᏴᏌᏗᏒᎢ ᏥᎨᏒ",
        "relativeTimePattern-count-one" : "{0} ᎤᏕᏘᏴᏌᏗᏒᎢ ᏥᎨᏒ"
      }
    },
    "month" : {
      "displayName" : "ᎧᎸᎢ",
      "relative-type-0" : "ᎯᎠ ᎧᎸᎢ",
      "relative-type-1" : "ᏔᎵᏁ ᎧᎸᎢ",
      "relative-type--1" : "ᎧᎸᎢ ᏥᎨᏒ",
      "relativeTime-type-future" : {
        "relativeTimePattern-count-other" : "ᎾᎿ {0} ᏗᎧᎸᎢ",
        "relativeTimePattern-count-one" : "ᎾᎿ {0} ᎧᎸᎢ"
      },
      "relativeTime-type-past" : {
        "relativeTimePattern-count-other" : "ᎾᎿ {0} ᏗᎧᎸᎢ ᏥᎨᏒ",
        "relativeTimePattern-count-one" : "ᎾᎿ {0} ᎧᎸᎢ ᏥᎨᏒ"
      }
    },
    "day" : {
      "displayName" : "ᎢᎦ",
      "relative-type-0" : "ᎪᎯ ᎢᎦ",
      "relative-type-1" : "ᏌᎾᎴᎢ",
      "relative-type--1" : "ᏒᎯ",
      "relativeTime-type-future" : {
        "relativeTimePattern-count-other" : "ᎾᎿ {0} ᎯᎸᏍᎩ ᏧᏒᎯᏛ",
        "relativeTimePattern-count-one" : "ᎾᎿ {0} ᎢᎦ"
      },
      "relativeTime-type-past" : {
        "relativeTimePattern-count-other" : "{0} ᎯᎸᏍᎩ ᏧᏒᎯᏛ ᏥᎨᏒ",
        "relativeTimePattern-count-one" : "{0} ᎢᎦ ᏥᎨᏒ"
      }
    },
    "hour" : {
      "displayName" : "ᏑᏟᎶᏓ",
      "relative-type-0" : "ᎯᎠ ᏑᏟᎶᏓ",
      "relativeTime-type-future" : {
        "relativeTimePattern-count-other" : "ᎾᎿ {0} ᎢᏳᏟᎶᏓ",
        "relativeTimePattern-count-one" : "ᎾᎿ {0} ᏑᏟᎶᏓ"
      },
      "relativeTime-type-past" : {
        "relativeTimePattern-count-other" : "{0} ᎢᏳᏟᎶᏓ ᏥᎨᏒ",
        "relativeTimePattern-count-one" : "{0} ᏑᏟᎶᏓ ᏥᎨᏒ"
      }
    },
    "minute" : {
      "displayName" : "ᎢᏯᏔᏬᏍᏔᏅ",
      "relative-type-0" : "ᎯᎠ ᎢᏯᏔᏬᏍᏔᏅ",
      "relativeTime-type-future" : {
        "relativeTimePattern-count-other" : "ᎾᎿ {0} ᎢᏯᏔᏬᏍᏔᏅ",
        "relativeTimePattern-count-one" : "ᎾᎿ {0} ᎢᏯᏔᏬᏍᏔᏅ"
      },
      "relativeTime-type-past" : {
        "relativeTimePattern-count-other" : "ᎾᎿ {0} ᎢᏯᏔᏬᏍᏔᏅ ᏥᎨᏒ",
        "relativeTimePattern-count-one" : "ᎾᎿ {0} ᎢᏯᏔᏬᏍᏔᏅ ᏥᎨᏒ"
      }
    },
    "second" : {
      "displayName" : "ᎠᏎᏢ",
      "relative-type-0" : "ᏃᏊ",
      "relativeTime-type-future" : {
        "relativeTimePattern-count-other" : "ᎾᎿ {0} ᏓᏓᎾᏩᏍᎬ ᏥᎨᏒ",
        "relativeTimePattern-count-one" : "ᎾᎿ {0} ᎠᏎᏢ"
      },
      "relativeTime-type-past" : {
        "relativeTimePattern-count-other" : "{0} ᏓᏓᎾᏩᏍᎬ ᏥᎨᏒ",
        "relativeTimePattern-count-one" : "{0} ᎠᏎᏢ ᏥᎨᏒ"
      }
    }
  }
}