{
  "language" : "sr",
  "territories" : {
    "af" : "Јужноафричка Република",
    "af-NA" : "Намибија",
    "agq" : "Камерун",
    "ak" : "Гана",
    "am" : "Етиопија",
    "ar-AE" : "Уједињени Арапски Емирати",
    "ar-BH" : "Бахреин",
    "ar-DJ" : "Џибути",
    "ar-DZ" : "Алжир",
    "ar-EG" : "Египат",
    "ar-EH" : "Западна Сахара",
    "ar-ER" : "Еритреја",
    "ar-IL" : "Израел",
    "ar-IQ" : "Ирак",
    "ar-JO" : "Јордан",
    "ar-KM" : "Коморска Острва",
    "ar-KW" : "Кувајт",
    "ar-LB" : "Либан",
    "ar-LY" : "Либија",
    "ar-MA" : "Мароко",
    "ar-MR" : "Мауританија",
    "ar-OM" : "Оман",
    "ar-PS" : "Палестинске територије",
    "ar-QA" : "Катар",
    "ar-SA" : "Саудијска Арабија",
    "ar-SD" : "Судан",
    "ar-SO" : "Сомалија",
    "ar-SS" : "Јужни Судан",
    "ar-SY" : "Сирија",
    "ar-TD" : "Чад",
    "ar-TN" : "Тунис",
    "ar-YE" : "Јемен",
    "as" : "Индија",
    "asa" : "Танзанија",
    "ast" : "Шпанија",
    "az-Cyrl" : "Азербејџан",
    "az-Latn" : "Азербејџан",
    "bas" : "Камерун",
    "be" : "Бјелорусија",
    "bem" : "Замбија",
    "bez" : "Танзанија",
    "bg" : "Бугарска",
    "bm" : "Мали",
    "bn" : "Бангладеш",
    "bn-IN" : "Индија",
    "bo" : "Кина",
    "bo-IN" : "Индија",
    "br" : "Француска",
    "brx" : "Индија",
    "bs-Cyrl" : "Босна и Херцеговина",
    "bs-Latn" : "Босна и Херцеговина",
    "ca" : "Шпанија",
    "ca-AD" : "Андора",
    "ca-ES-VALENCIA" : "Шпанија",
    "ca-FR" : "Француска",
    "ca-IT" : "Италија",
    "ccp" : "Бангладеш",
    "ccp-IN" : "Индија",
    "ce" : "Русија",
    "cgg" : "Уганда",
    "chr" : "Сједињене Државе",
    "ckb" : "Ирак",
    "ckb-IR" : "Иран",
    "cs" : "Чешка Република",
    "cu" : "Русија",
    "cy" : "Уједињено Краљевство",
    "da" : "Данска",
    "da-GL" : "Гренланд",
    "dav" : "Кенија",
    "de" : "Њемачка",
    "de-AT" : "Аустрија",
    "de-BE" : "Белгија",
    "de-CH" : "Швајцарска",
    "de-IT" : "Италија",
    "de-LI" : "Лихтенштајн",
    "de-LU" : "Луксембург",
    "dje" : "Нигер",
    "dsb" : "Њемачка",
    "dua" : "Камерун",
    "dyo" : "Сенегал",
    "dz" : "Бутан",
    "ebu" : "Кенија",
    "ee" : "Гана",
    "ee-TG" : "Того",
    "el" : "Грчка",
    "el-CY" : "Кипар",
    "en" : "Сједињене Државе",
    "en-AG" : "Антигва и Барбуда",
    "en-AI" : "Ангвила",
    "en-AS" : "Америчка Самоа",
    "en-AT" : "Аустрија",
    "en-AU" : "Аустралија",
    "en-BB" : "Барбадос",
    "en-BE" : "Белгија",
    "en-BI" : "Бурунди",
    "en-BM" : "Бермуда",
    "en-BS" : "Бахами",
    "en-BW" : "Боцвана",
    "en-BZ" : "Белизе",
    "en-CA" : "Канада",
    "en-CC" : "Кокосова (Килингова) Острва",
    "en-CH" : "Швајцарска",
    "en-CK" : "Кукова Острва",
    "en-CM" : "Камерун",
    "en-CX" : "Божићно Острво",
    "en-CY" : "Кипар",
    "en-DE" : "Њемачка",
    "en-DG" : "Дијего Гарсија",
    "en-DK" : "Данска",
    "en-DM" : "Доминика",
    "en-ER" : "Еритреја",
    "en-FI" : "Финска",
    "en-FJ" : "Фиџи",
    "en-FK" : "Фокландска Острва",
    "en-FM" : "Микронезија",
    "en-GB" : "Уједињено Краљевство",
    "en-GD" : "Гренада",
    "en-GG" : "Гернзи",
    "en-GH" : "Гана",
    "en-GI" : "Гибралтар",
    "en-GM" : "Гамбија",
    "en-GU" : "Гуам",
    "en-GY" : "Гвајана",
    "en-HK" : "САР Хонгконг (Кина)",
    "en-IE" : "Ирска",
    "en-IL" : "Израел",
    "en-IM" : "Острво Ман",
    "en-IN" : "Индија",
    "en-IO" : "Британска територија Индијског океана",
    "en-JE" : "Џерзи",
    "en-JM" : "Јамајка",
    "en-KE" : "Кенија",
    "en-KI" : "Кирибати",
    "en-KN" : "Свети Китс и Невис",
    "en-KY" : "Кајманска Острва",
    "en-LC" : "Света Луција",
    "en-LR" : "Либерија",
    "en-LS" : "Лесото",
    "en-MG" : "Мадагаскар",
    "en-MH" : "Маршалска Острва",
    "en-MO" : "САР Макао",
    "en-MP" : "Северна Маријанска Острва",
    "en-MS" : "Монсерат",
    "en-MT" : "Малта",
    "en-MU" : "Маурицијус",
    "en-MW" : "Малави",
    "en-MY" : "Малезија",
    "en-NA" : "Намибија",
    "en-NF" : "Острво Норфок",
    "en-NG" : "Нигерија",
    "en-NL" : "Холандија",
    "en-NR" : "Науру",
    "en-NU" : "Ниуе",
    "en-NZ" : "Нови Зеланд",
    "en-PG" : "Папуа Нова Гвинеја",
    "en-PH" : "Филипини",
    "en-PK" : "Пакистан",
    "en-PN" : "Питкерн",
    "en-PR" : "Порторико",
    "en-PW" : "Палау",
    "en-RW" : "Руанда",
    "en-SB" : "Соломонска Острва",
    "en-SC" : "Сејшели",
    "en-SD" : "Судан",
    "en-SE" : "Шведска",
    "en-SG" : "Сингапур",
    "en-SH" : "Света Јелена",
    "en-SI" : "Словенија",
    "en-SL" : "Сијера Леоне",
    "en-SS" : "Јужни Судан",
    "en-SX" : "Свети Мартин (Холандија)",
    "en-SZ" : "Свазиленд",
    "en-TC" : "Острва Туркс и Каикос",
    "en-TK" : "Токелау",
    "en-TO" : "Тонга",
    "en-TT" : "Тринидад и Тобаго",
    "en-TV" : "Тувалу",
    "en-TZ" : "Танзанија",
    "en-UG" : "Уганда",
    "en-UM" : "Мања удаљена острва САД",
    "en-US-POSIX" : "Сједињене Државе",
    "en-VC" : "Свети Винсент и Гренадини",
    "en-VG" : "Британска Дјевичанска Острва",
    "en-VI" : "Америчка Дјевичанска Острва",
    "en-VU" : "Вануату",
    "en-WS" : "Самоа",
    "en-ZA" : "Јужноафричка Република",
    "en-ZM" : "Замбија",
    "en-ZW" : "Зимбабве",
    "es" : "Шпанија",
    "es-AR" : "Аргентина",
    "es-BO" : "Боливија",
    "es-BR" : "Бразил",
    "es-BZ" : "Белизе",
    "es-CL" : "Чиле",
    "es-CO" : "Колумбија",
    "es-CR" : "Костарика",
    "es-CU" : "Куба",
    "es-DO" : "Доминиканска Република",
    "es-EA" : "Сеута и Мелиља",
    "es-EC" : "Еквадор",
    "es-GQ" : "Екваторијална Гвинеја",
    "es-GT" : "Гватемала",
    "es-HN" : "Хондурас",
    "es-IC" : "Канарска Острва",
    "es-MX" : "Мексико",
    "es-NI" : "Никарагва",
    "es-PA" : "Панама",
    "es-PE" : "Перу",
    "es-PH" : "Филипини",
    "es-PR" : "Порторико",
    "es-PY" : "Парагвај",
    "es-SV" : "Салвадор",
    "es-US" : "Сједињене Државе",
    "es-UY" : "Уругвај",
    "es-VE" : "Венецуела",
    "et" : "Естонија",
    "eu" : "Шпанија",
    "ewo" : "Камерун",
    "fa" : "Иран",
    "fa-AF" : "Авганистан",
    "ff" : "Сенегал",
    "ff-CM" : "Камерун",
    "ff-GN" : "Гвинеја",
    "ff-MR" : "Мауританија",
    "fi" : "Финска",
    "fil" : "Филипини",
    "fo" : "Фарска Острва",
    "fo-DK" : "Данска",
    "fr" : "Француска",
    "fr-BE" : "Белгија",
    "fr-BF" : "Буркина Фасо",
    "fr-BI" : "Бурунди",
    "fr-BJ" : "Бенин",
    "fr-BL" : "Свети Бартоломеј",
    "fr-CA" : "Канада",
    "fr-CD" : "Конго - Киншаса",
    "fr-CF" : "Централноафричка Република",
    "fr-CG" : "Конго",
    "fr-CH" : "Швајцарска",
    "fr-CI" : "Обала Слоноваче (Кот д’Ивоар)",
    "fr-CM" : "Камерун",
    "fr-DJ" : "Џибути",
    "fr-DZ" : "Алжир",
    "fr-GA" : "Габон",
    "fr-GF" : "Француска Гвајана",
    "fr-GN" : "Гвинеја",
    "fr-GP" : "Гваделуп",
    "fr-GQ" : "Екваторијална Гвинеја",
    "fr-HT" : "Хаити",
    "fr-KM" : "Коморска Острва",
    "fr-LU" : "Луксембург",
    "fr-MA" : "Мароко",
    "fr-MC" : "Монако",
    "fr-MF" : "Свети Мартин (Француска)",
    "fr-MG" : "Мадагаскар",
    "fr-ML" : "Мали",
    "fr-MQ" : "Мартиник",
    "fr-MR" : "Мауританија",
    "fr-MU" : "Маурицијус",
    "fr-NC" : "Нова Каледонија",
    "fr-NE" : "Нигер",
    "fr-PF" : "Француска Полинезија",
    "fr-PM" : "Свети Пјер и Микелон",
    "fr-RE" : "Реунион",
    "fr-RW" : "Руанда",
    "fr-SC" : "Сејшели",
    "fr-SN" : "Сенегал",
    "fr-SY" : "Сирија",
    "fr-TD" : "Чад",
    "fr-TG" : "Того",
    "fr-TN" : "Тунис",
    "fr-VU" : "Вануату",
    "fr-WF" : "Валис и Футуна",
    "fr-YT" : "Мајот",
    "fur" : "Италија",
    "fy" : "Холандија",
    "ga" : "Ирска",
    "gd" : "Уједињено Краљевство",
    "gl" : "Шпанија",
    "gsw" : "Швајцарска",
    "gsw-FR" : "Француска",
    "gsw-LI" : "Лихтенштајн",
    "gu" : "Индија",
    "guz" : "Кенија",
    "gv" : "Острво Ман",
    "ha" : "Нигерија",
    "ha-GH" : "Гана",
    "ha-NE" : "Нигер",
    "haw" : "Сједињене Државе",
    "he" : "Израел",
    "hi" : "Индија",
    "hr" : "Хрватска",
    "hr-BA" : "Босна и Херцеговина",
    "hsb" : "Њемачка",
    "hu" : "Мађарска",
    "hy" : "Јерменија",
    "id" : "Индонезија",
    "ig" : "Нигерија",
    "ii" : "Кина",
    "is" : "Исланд",
    "it" : "Италија",
    "it-CH" : "Швајцарска",
    "it-SM" : "Сан Марино",
    "it-VA" : "Ватикан",
    "ja" : "Јапан",
    "jgo" : "Камерун",
    "jmc" : "Танзанија",
    "ka" : "Грузија",
    "kab" : "Алжир",
    "kam" : "Кенија",
    "kde" : "Танзанија",
    "kea" : "Кабо Верде",
    "khq" : "Мали",
    "ki" : "Кенија",
    "kk" : "Казахстан",
    "kkj" : "Камерун",
    "kl" : "Гренланд",
    "kln" : "Кенија",
    "km" : "Камбоџа",
    "kn" : "Индија",
    "ko" : "Јужна Кореја",
    "ko-KP" : "Северна Кореја",
    "kok" : "Индија",
    "ks" : "Индија",
    "ksb" : "Танзанија",
    "ksf" : "Камерун",
    "ksh" : "Њемачка",
    "kw" : "Уједињено Краљевство",
    "ky" : "Киргистан",
    "lag" : "Танзанија",
    "lb" : "Луксембург",
    "lg" : "Уганда",
    "lkt" : "Сједињене Државе",
    "ln" : "Конго - Киншаса",
    "ln-AO" : "Ангола",
    "ln-CF" : "Централноафричка Република",
    "ln-CG" : "Конго",
    "lo" : "Лаос",
    "lrc" : "Иран",
    "lrc-IQ" : "Ирак",
    "lt" : "Литванија",
    "lu" : "Конго - Киншаса",
    "luo" : "Кенија",
    "luy" : "Кенија",
    "lv" : "Летонија",
    "mas" : "Кенија",
    "mas-TZ" : "Танзанија",
    "mer" : "Кенија",
    "mfe" : "Маурицијус",
    "mg" : "Мадагаскар",
    "mgh" : "Мозамбик",
    "mgo" : "Камерун",
    "mk" : "Македонија",
    "ml" : "Индија",
    "mn" : "Монголија",
    "mr" : "Индија",
    "ms" : "Малезија",
    "ms-BN" : "Брунеј",
    "ms-SG" : "Сингапур",
    "mt" : "Малта",
    "mua" : "Камерун",
    "my" : "Мијанмар (Бурма)",
    "mzn" : "Иран",
    "naq" : "Намибија",
    "nb" : "Норвешка",
    "nb-SJ" : "Свалбард и Јан Мајен",
    "nd" : "Зимбабве",
    "nds" : "Њемачка",
    "nds-NL" : "Холандија",
    "ne" : "Непал",
    "ne-IN" : "Индија",
    "nl" : "Холандија",
    "nl-AW" : "Аруба",
    "nl-BE" : "Белгија",
    "nl-BQ" : "Карипска Холандија",
    "nl-CW" : "Курасао",
    "nl-SR" : "Суринам",
    "nl-SX" : "Свети Мартин (Холандија)",
    "nmg" : "Камерун",
    "nn" : "Норвешка",
    "nnh" : "Камерун",
    "nus" : "Јужни Судан",
    "nyn" : "Уганда",
    "om" : "Етиопија",
    "om-KE" : "Кенија",
    "or" : "Индија",
    "os" : "Грузија",
    "os-RU" : "Русија",
    "pa-Arab" : "Пакистан",
    "pa-Guru" : "Индија",
    "pl" : "Пољска",
    "ps" : "Авганистан",
    "pt" : "Бразил",
    "pt-AO" : "Ангола",
    "pt-CH" : "Швајцарска",
    "pt-CV" : "Кабо Верде",
    "pt-GQ" : "Екваторијална Гвинеја",
    "pt-GW" : "Гвинеја-Бисао",
    "pt-LU" : "Луксембург",
    "pt-MO" : "САР Макао",
    "pt-MZ" : "Мозамбик",
    "pt-PT" : "Португалија",
    "pt-ST" : "Сао Томе и Принципе",
    "pt-TL" : "Тимор-Лесте (Источни Тимор)",
    "qu" : "Перу",
    "qu-BO" : "Боливија",
    "qu-EC" : "Еквадор",
    "rm" : "Швајцарска",
    "rn" : "Бурунди",
    "ro" : "Румунија",
    "ro-MD" : "Молдавија",
    "rof" : "Танзанија",
    "ru" : "Русија",
    "ru-BY" : "Бјелорусија",
    "ru-KG" : "Киргистан",
    "ru-KZ" : "Казахстан",
    "ru-MD" : "Молдавија",
    "ru-UA" : "Украјина",
    "rw" : "Руанда",
    "rwk" : "Танзанија",
    "sah" : "Русија",
    "saq" : "Кенија",
    "sbp" : "Танзанија",
    "sd" : "Пакистан",
    "se" : "Норвешка",
    "se-FI" : "Финска",
    "se-SE" : "Шведска",
    "seh" : "Мозамбик",
    "ses" : "Мали",
    "sg" : "Централноафричка Република",
    "shi-Latn" : "Мароко",
    "shi-Tfng" : "Мароко",
    "si" : "Шри Ланка",
    "sk" : "Словачка",
    "sl" : "Словенија",
    "smn" : "Финска",
    "sn" : "Зимбабве",
    "so" : "Сомалија",
    "so-DJ" : "Џибути",
    "so-ET" : "Етиопија",
    "so-KE" : "Кенија",
    "sq" : "Албанија",
    "sq-MK" : "Македонија",
    "sq-XK" : "Косово",
    "sr-Cyrl" : "Србија",
    "sr-Cyrl-BA" : "Босна и Херцеговина",
    "sr-Cyrl-ME" : "Црна Гора",
    "sr-Cyrl-XK" : "Косово",
    "sr-Latn" : "Србија",
    "sr-Latn-BA" : "Босна и Херцеговина",
    "sr-Latn-ME" : "Црна Гора",
    "sr-Latn-XK" : "Косово",
    "sv" : "Шведска",
    "sv-AX" : "Оландска Острва",
    "sv-FI" : "Финска",
    "sw" : "Танзанија",
    "sw-CD" : "Конго - Киншаса",
    "sw-KE" : "Кенија",
    "sw-UG" : "Уганда",
    "ta" : "Индија",
    "ta-LK" : "Шри Ланка",
    "ta-MY" : "Малезија",
    "ta-SG" : "Сингапур",
    "te" : "Индија",
    "teo" : "Уганда",
    "teo-KE" : "Кенија",
    "tg" : "Таџикистан",
    "th" : "Тајланд",
    "ti" : "Етиопија",
    "ti-ER" : "Еритреја",
    "tk" : "Туркменистан",
    "to" : "Тонга",
    "tr" : "Турска",
    "tr-CY" : "Кипар",
    "tt" : "Русија",
    "twq" : "Нигер",
    "tzm" : "Мароко",
    "ug" : "Кина",
    "uk" : "Украјина",
    "ur" : "Пакистан",
    "ur-IN" : "Индија",
    "uz-Arab" : "Авганистан",
    "uz-Cyrl" : "Узбекистан",
    "uz-Latn" : "Узбекистан",
    "vai-Latn" : "Либерија",
    "vai-Vaii" : "Либерија",
    "vi" : "Вијетнам",
    "vun" : "Танзанија",
    "wae" : "Швајцарска",
    "wo" : "Сенегал",
    "xog" : "Уганда",
    "yav" : "Камерун",
    "yo" : "Нигерија",
    "yo-BJ" : "Бенин",
    "yue-Hans" : "Кина",
    "yue-Hant" : "САР Хонгконг (Кина)",
    "zgh" : "Мароко",
    "zh-Hans" : "Кина",
    "zh-Hans-HK" : "САР Хонгконг (Кина)",
    "zh-Hans-MO" : "САР Макао",
    "zh-Hans-SG" : "Сингапур",
    "zh-Hant" : "Тајван",
    "zh-Hant-HK" : "САР Хонгконг (Кина)",
    "zh-Hant-MO" : "САР Макао",
    "zu" : "Јужноафричка Република"
  }
}